create_drf_app/__init__.py
create_drf_app/main.py
create_drf_app/templates/basic/cookiecutter.json
create_drf_app/templates/basic/{{ cookiecutter.project_name }}/.gitignore
create_drf_app/templates/basic/{{ cookiecutter.project_name }}/manage.py
create_drf_app/templates/basic/{{ cookiecutter.project_name }}/requirements.txt
create_drf_app/templates/basic/{{ cookiecutter.project_name }}/users/__init__.py
create_drf_app/templates/basic/{{ cookiecutter.project_name }}/users/admin.py
create_drf_app/templates/basic/{{ cookiecutter.project_name }}/users/apps.py
create_drf_app/templates/basic/{{ cookiecutter.project_name }}/users/migrations/__init__.py
create_drf_app/templates/basic/{{ cookiecutter.project_name }}/users/models.py
create_drf_app/templates/basic/{{ cookiecutter.project_name }}/users/serializers.py
create_drf_app/templates/basic/{{ cookiecutter.project_name }}/users/tests.py
create_drf_app/templates/basic/{{ cookiecutter.project_name }}/users/urls.py
create_drf_app/templates/basic/{{ cookiecutter.project_name }}/users/views.py
create_drf_app/templates/basic/{{ cookiecutter.project_name }}/{{ cookiecutter.project_name }}/__init__.py
create_drf_app/templates/basic/{{ cookiecutter.project_name }}/{{ cookiecutter.project_name }}/asgi.py
create_drf_app/templates/basic/{{ cookiecutter.project_name }}/{{ cookiecutter.project_name }}/models.py
create_drf_app/templates/basic/{{ cookiecutter.project_name }}/{{ cookiecutter.project_name }}/settings/base.py
create_drf_app/templates/basic/{{ cookiecutter.project_name }}/{{ cookiecutter.project_name }}/settings/local.py
create_drf_app/templates/basic/{{ cookiecutter.project_name }}/{{ cookiecutter.project_name }}/settings/production.py
create_drf_app/templates/basic/{{ cookiecutter.project_name }}/{{ cookiecutter.project_name }}/urls.py
create_drf_app/templates/basic/{{ cookiecutter.project_name }}/{{ cookiecutter.project_name }}/wsgi.py
create_drf_app-0.2.1.dist-info/entry_points.txt
create_drf_app-0.2.1.dist-info/LICENSE.md
create_drf_app-0.2.1.dist-info/WHEEL
create_drf_app-0.2.1.dist-info/METADATA
create_drf_app-0.2.1.dist-info/RECORD
