Metadata-Version: 2.1
Name: create-drf-app
Version: 0.2.1
Summary: Starting a DRF project made easy
Home-page: https://github.com/MohammedBajuaifer/create-drf-app
License: MIT
Keywords: scaffold,drf,django,cli,commands
Author: Mohammed Bajuaifer
Author-email: m.bajuaifer@gmail.com
Requires-Python: >=3.8,<4.0
Classifier: License :: OSI Approved :: MIT License
Classifier: Programming Language :: Python :: 3
Classifier: Programming Language :: Python :: 3.8
Classifier: Programming Language :: Python :: 3.9
Classifier: Programming Language :: Python :: 3.10
Requires-Dist: cookiecutter (==2.1.1)
Requires-Dist: typer (>=0.6.1,<0.7.0)
Project-URL: Repository, https://github.com/MohammedBajuaifer/create-drf-app
